README.md
setup.py
rosbag2_api/__init__.py
rosbag2_api/read_bag.py
rosbag2_api/save_csv_file.py
rosbag2_api.egg-info/PKG-INFO
rosbag2_api.egg-info/SOURCES.txt
rosbag2_api.egg-info/dependency_links.txt
rosbag2_api.egg-info/requires.txt
rosbag2_api.egg-info/top_level.txt