Metadata-Version: 2.1
Name: rosbag2-api
Version: 0.0.1
Summary: Package for reading bag files and convert to csv.
Home-page: https://github.com/biospine/reading_rosbag
Author: Ana de Sousa
Author-email: anacsousa@lara.unb.br
License: GNU GPLv3
Keywords: rosbag
Platform: UNKNOWN
Classifier: Development Status :: 5 - Production/Stable
Classifier: Programming Language :: Python :: 3
Classifier: License :: OSI Approved :: MIT License
Classifier: Operating System :: OS Independent
Requires-Python: >=3.6
